RLE/t_flipflop.v
module t_flipflop(
clock ,
toggle ,
reset ,
q ,
not_q
);

//input ports
input clock;
input toggle;
input reset; 

//output ports
output q;
output not_q;

//internals 
wire clock;
wire toggle;
wire reset;
reg q;
reg not_q;

//code
always @ (posedge clock or posedge reset)
begin: FLIPFLOP
	if (reset == 1'b1) begin
		q = 1'b0;
		not_q = 1'b1;
	end
		
	else if (reset == 1'b0) begin
		not_q = (~toggle & ~q)|(toggle & q);
		q = (toggle & ~q)|(q & ~toggle);	
	end
end
endmodule

RLE/t_flipflop_tb.v
`include "t_flipflop.v"
module t_flipflop_tb();

reg clock;
reg toggle;
reg reset;
wire q;
wire not_q;

initial begin
	$dumpfile("tff.vcd");
	$dumpvars(0,t_flipflop_tb);
	
	reset = 0;
	clock = 1;
	toggle = 0;
	
	#1 reset = 1;
	#2 reset = 0;
	#1 toggle = 1;
	#1 toggle = 0;
	#1 toggle = 1;
	#3 toggle = 0;
	#3 toggle = 1;
	#2 toggle = 0;
	#10 $finish;
end

always begin
 #1 clock = ~clock;
end

t_flipflop tff (
clock,
toggle,
reset,
q,
not_q
);

endmodule

RLE/tff.vcd
$date
	Sun Oct 01 15:34:36 2017
$end
$version
	Icarus Verilog
$end
$timescale
	1s
$end
$scope module t_flipflop_tb $end
$var wire 1 ! q $end
$var wire 1 " not_q $end
$var reg 1 # clock $end
$var reg 1 $ reset $end
$var reg 1 % toggle $end
$scope module tff $end
$var wire 1 # clock $end
$var wire 1 $ reset $end
$var wire 1 % toggle $end
$var reg 1 " not_q $end
$var reg 1 ! q $end
$upscope $end
$upscope $end
$enddefinitions $end
#0
$dumpvars
0%
0$
1#
x"
x!
$end
#1
0#
1$
#2
1"
0!
1#
#3
0#
0$
#4
1!
0"
1#
1%
#5
0#
0%
#6
0!
1"
1#
1%
#7
0#
#8
1!
0"
1#
#9
0#
0%
#10
1#
#11
0#
#12
0!
1"
1#
1%
#13
0#
#14
1#
0%
