RLE/t_flipflop.v
module t_flipflop(
clock ,
toggle ,
reset ,
q ,
not_q
);

//input ports
input clock;
input toggle;
input reset; 

//output ports
output q;
output not_q;

//internals 
wire clock;
wire toggle;
wire reset;
reg q;
reg not_q;

//code
always @ (posedge clock or posedge reset)
begin: FLIPFLOP
	if (reset == 1'b1) begin
		q = 1'b0;
		not_q = 1'b1;
	end
		
	else if (reset == 1'b0) begin
		not_q = (~toggle & ~q)|(toggle & q);
		q = (toggle & ~q)|(q & ~toggle);	
	end
end
endmodule

RLE/upcounter.v
`include "t_flipflop.v"

module upcounter(
clock,
reset,
count,
overflow
);

//input ports
input clock;
input reset;

//output ports
output [7:0] count;
output overflow;

//internals
wire clock;
wire reset;
reg [7:0] toggle;
wire [7:0] count;
wire [7:0] ncount;
reg overflow;

//code

always @ (posedge count or ncount or toggle or reset)
begin : BICOUNTER
	if (reset == 1) begin			
		toggle[7:0] = 7'b0000011;		
		overflow = 1'b0;		
	end 
	else if (reset == 0) begin
		
		toggle[0] = 1'b1;					//bit 0
		toggle[1] = count[0];  				//bit 1
		toggle[2] = toggle[1]&count[1];
		toggle[3] = toggle[2]&count[2];
		toggle[4] = toggle[3]&count[3];
		toggle[5] = toggle[4]&count[4];
		toggle[6] = toggle[5]&count[5];
		toggle[7] = toggle[6]&count[6];		
		overflow = &count;

	end
end

t_flipflop tff0(
clock,
toggle[0],
reset,
ncount[0],
count[0]
);

t_flipflop tff1(
clock,
toggle[1],
reset,
count[1],
ncount[1]
);

t_flipflop tff2(
clock,
toggle[2],
reset,
count[2],
ncount[2]
);

t_flipflop tff3(
clock,
toggle[3],
reset,
count[3],
ncount[3]
);

t_flipflop tff4(
clock,
toggle[4],
reset,
count[4],
ncount[4]
);

t_flipflop tff5(
clock,
toggle[5],
reset,
count[5],
ncount[5]
);

t_flipflop tff6(
clock,
toggle[6],
reset,
count[6],
ncount[6]
);

t_flipflop tff7(
clock,
toggle[7],
reset,
count[7],
ncount[7]
);


endmodule

RLE/upcounter_tb.v
`include "upcounter.v"
module upcounter_tb();

reg clock;
reg reset;
wire [7:0] count;
wire overflow;

initial begin
	$dumpfile("upcounter.vcd");
	$dumpvars(0,upcounter_tb);
	
	clock = 1;
	reset = 0;
	
	#3 reset = 1;
	#2 reset = 0;	
	#600 $finish;
	
end

always begin
	#1 clock = ~clock;
end

upcounter U_upcounter(
clock,
reset,
count,
overflow
);

endmodule

RLE/upcounter.vcd
$date
	Sat Oct 07 15:53:39 2017
$end
$version
	Icarus Verilog
$end
$timescale
	1s
$end
$scope module upcounter_tb $end
$var wire 1 ! overflow $end
$var wire 8 " count [7:0] $end
$var reg 1 # clock $end
$var reg 1 $ reset $end
$scope module U_upcounter $end
$var wire 1 # clock $end
$var wire 1 $ reset $end
$var wire 8 % ncount [7:0] $end
$var wire 8 & count [7:0] $end
$var reg 1 ! overflow $end
$var reg 8 ' toggle [7:0] $end
$scope module tff0 $end
$var wire 1 # clock $end
$var wire 1 $ reset $end
$var wire 1 ( toggle $end
$var reg 1 ) not_q $end
$var reg 1 * q $end
$scope begin FLIPFLOP $end
$upscope $end
$upscope $end
$scope module tff1 $end
$var wire 1 # clock $end
$var wire 1 $ reset $end
$var wire 1 + toggle $end
$var reg 1 , not_q $end
$var reg 1 - q $end
$scope begin FLIPFLOP $end
$upscope $end
$upscope $end
$scope module tff2 $end
$var wire 1 # clock $end
$var wire 1 $ reset $end
$var wire 1 . toggle $end
$var reg 1 / not_q $end
$var reg 1 0 q $end
$scope begin FLIPFLOP $end
$upscope $end
$upscope $end
$scope module tff3 $end
$var wire 1 # clock $end
$var wire 1 $ reset $end
$var wire 1 1 toggle $end
$var reg 1 2 not_q $end
$var reg 1 3 q $end
$scope begin FLIPFLOP $end
$upscope $end
$upscope $end
$scope module tff4 $end
$var wire 1 # clock $end
$var wire 1 $ reset $end
$var wire 1 4 toggle $end
$var reg 1 5 not_q $end
$var reg 1 6 q $end
$scope begin FLIPFLOP $end
$upscope $end
$upscope $end
$scope module tff5 $end
$var wire 1 # clock $end
$var wire 1 $ reset $end
$var wire 1 7 toggle $end
$var reg 1 8 not_q $end
$var reg 1 9 q $end
$scope begin FLIPFLOP $end
$upscope $end
$upscope $end
$scope module tff6 $end
$var wire 1 # clock $end
$var wire 1 $ reset $end
$var wire 1 : toggle $end
$var reg 1 ; not_q $end
$var reg 1 < q $end
$scope begin FLIPFLOP $end
$upscope $end
$upscope $end
$scope module tff7 $end
$var wire 1 # clock $end
$var wire 1 $ reset $end
$var wire 1 = toggle $end
$var reg 1 > not_q $end
$var reg 1 ? q $end
$scope begin FLIPFLOP $end
$upscope $end
$upscope $end
$scope begin BICOUNTER $end
$upscope $end
$upscope $end
$upscope $end
$enddefinitions $end
#0
$dumpvars
x?
x>
x=
x<
x;
x:
x9
x8
x7
x6
x5
x4
x3
x2
x1
x0
x/
x.
x-
x,
x+
x*
x)
1(
bx1 '
bx &
bx %
0$
1#
bx "
x!
$end
#1
0#
#2
1#
#3
1+
0.
01
04
07
0:
0=
1>
0?
1;
0<
18
09
15
06
12
03
1/
00
1,
0-
b1 "
b1 &
1)
b11111110 %
0*
0!
b11 '
0#
1$
#4
1#
#5
0#
0$
#6
0+
b1 '
1-
0,
b11111101 %
1*
b10 "
b10 &
0)
1#
#7
0#
#8
1.
1+
b111 '
b11111100 %
0*
b11 "
b11 &
1)
1#
#9
0#
#10
0.
0+
b1 '
10
0/
0-
1,
b11111011 %
1*
b100 "
b100 &
0)
1#
#11
0#
#12
1+
b11 '
b11111010 %
0*
b101 "
b101 &
1)
1#
#13
0#
#14
0+
b1 '
1-
0,
b11111001 %
1*
b110 "
b110 &
0)
1#
#15
0#
#16
11
1.
1+
b1111 '
b11111000 %
0*
b111 "
b111 &
1)
1#
#17
0#
#18
01
0.
0+
b1 '
13
02
00
1/
0-
1,
b11110111 %
1*
b1000 "
b1000 &
0)
1#
#19
0#
#20
1+
b11 '
b11110110 %
0*
b1001 "
b1001 &
1)
1#
#21
0#
#22
0+
b1 '
1-
0,
b11110101 %
1*
b1010 "
b1010 &
0)
1#
#23
0#
#24
1.
1+
b111 '
b11110100 %
0*
b1011 "
b1011 &
1)
1#
#25
0#
#26
0.
0+
b1 '
10
0/
0-
1,
b11110011 %
1*
b1100 "
b1100 &
0)
1#
#27
0#
#28
1+
b11 '
b11110010 %
0*
b1101 "
b1101 &
1)
1#
#29
0#
#30
0+
b1 '
1-
0,
b11110001 %
1*
b1110 "
b1110 &
0)
1#
#31
0#
#32
14
11
1.
1+
b11111 '
b11110000 %
0*
b1111 "
b1111 &
1)
1#
#33
0#
#34
04
01
0.
0+
b1 '
16
05
03
12
00
1/
0-
1,
b11101111 %
1*
b10000 "
b10000 &
0)
1#
#35
0#
#36
1+
b11 '
b11101110 %
0*
b10001 "
b10001 &
1)
1#
#37
0#
#38
0+
b1 '
1-
0,
b11101101 %
1*
b10010 "
b10010 &
0)
1#
#39
0#
#40
1.
1+
b111 '
b11101100 %
0*
b10011 "
b10011 &
1)
1#
#41
0#
#42
0.
0+
b1 '
10
0/
0-
1,
b11101011 %
1*
b10100 "
b10100 &
0)
1#
#43
0#
#44
1+
b11 '
b11101010 %
0*
b10101 "
b10101 &
1)
1#
#45
0#
#46
0+
b1 '
1-
0,
b11101001 %
1*
b10110 "
b10110 &
0)
1#
#47
0#
#48
11
1.
1+
b1111 '
b11101000 %
0*
b10111 "
b10111 &
1)
1#
#49
0#
#50
01
0.
0+
b1 '
13
02
00
1/
0-
1,
b11100111 %
1*
b11000 "
b11000 &
0)
1#
#51
0#
#52
1+
b11 '
b11100110 %
0*
b11001 "
b11001 &
1)
1#
#53
0#
#54
0+
b1 '
1-
0,
b11100101 %
1*
b11010 "
b11010 &
0)
1#
#55
0#
#56
1.
1+
b111 '
b11100100 %
0*
b11011 "
b11011 &
1)
1#
#57
0#
#58
0.
0+
b1 '
10
0/
0-
1,
b11100011 %
1*
b11100 "
b11100 &
0)
1#
#59
0#
#60
1+
b11 '
b11100010 %
0*
b11101 "
b11101 &
1)
1#
#61
0#
#62
0+
b1 '
1-
0,
b11100001 %
1*
b11110 "
b11110 &
0)
1#
#63
0#
#64
17
14
11
1.
1+
b111111 '
b11100000 %
0*
b11111 "
b11111 &
1)
1#
#65
0#
#66
07
04
01
0.
0+
b1 '
19
08
06
15
03
12
00
1/
0-
1,
b11011111 %
1*
b100000 "
b100000 &
0)
1#
#67
0#
#68
1+
b11 '
b11011110 %
0*
b100001 "
b100001 &
1)
1#
#69
0#
#70
0+
b1 '
1-
0,
b11011101 %
1*
b100010 "
b100010 &
0)
1#
#71
0#
#72
1.
1+
b111 '
b11011100 %
0*
b100011 "
b100011 &
1)
1#
#73
0#
#74
0.
0+
b1 '
10
0/
0-
1,
b11011011 %
1*
b100100 "
b100100 &
0)
1#
#75
0#
#76
1+
b11 '
b11011010 %
0*
b100101 "
b100101 &
1)
1#
#77
0#
#78
0+
b1 '
1-
0,
b11011001 %
1*
b100110 "
b100110 &
0)
1#
#79
0#
#80
11
1.
1+
b1111 '
b11011000 %
0*
b100111 "
b100111 &
1)
1#
#81
0#
#82
01
0.
0+
b1 '
13
02
00
1/
0-
1,
b11010111 %
1*
b101000 "
b101000 &
0)
1#
#83
0#
#84
1+
b11 '
b11010110 %
0*
b101001 "
b101001 &
1)
1#
#85
0#
#86
0+
b1 '
1-
0,
b11010101 %
1*
b101010 "
b101010 &
0)
1#
#87
0#
#88
1.
1+
b111 '
b11010100 %
0*
b101011 "
b101011 &
1)
1#
#89
0#
#90
0.
0+
b1 '
10
0/
0-
1,
b11010011 %
1*
b101100 "
b101100 &
0)
1#
#91
0#
#92
1+
b11 '
b11010010 %
0*
b101101 "
b101101 &
1)
1#
#93
0#
#94
0+
b1 '
1-
0,
b11010001 %
1*
b101110 "
b101110 &
0)
1#
#95
0#
#96
14
11
1.
1+
b11111 '
b11010000 %
0*
b101111 "
b101111 &
1)
1#
#97
0#
#98
04
01
0.
0+
b1 '
16
05
03
12
00
1/
0-
1,
b11001111 %
1*
b110000 "
b110000 &
0)
1#
#99
0#
#100
1+
b11 '
b11001110 %
0*
b110001 "
b110001 &
1)
1#
#101
0#
#102
0+
b1 '
1-
0,
b11001101 %
1*
b110010 "
b110010 &
0)
1#
#103
0#
#104
1.
1+
b111 '
b11001100 %
0*
b110011 "
b110011 &
1)
1#
#105
0#
#106
0.
0+
b1 '
10
0/
0-
1,
b11001011 %
1*
b110100 "
b110100 &
0)
1#
#107
0#
#108
1+
b11 '
b11001010 %
0*
b110101 "
b110101 &
1)
1#
#109
0#
#110
0+
b1 '
1-
0,
b11001001 %
1*
b110110 "
b110110 &
0)
1#
#111
0#
#112
11
1.
1+
b1111 '
b11001000 %
0*
b110111 "
b110111 &
1)
1#
#113
0#
#114
01
0.
0+
b1 '
13
02
00
1/
0-
1,
b11000111 %
1*
b111000 "
b111000 &
0)
1#
#115
0#
#116
1+
b11 '
b11000110 %
0*
b111001 "
b111001 &
1)
1#
#117
0#
#118
0+
b1 '
1-
0,
b11000101 %
1*
b111010 "
b111010 &
0)
1#
#119
0#
#120
1.
1+
b111 '
b11000100 %
0*
b111011 "
b111011 &
1)
1#
#121
0#
#122
0.
0+
b1 '
10
0/
0-
1,
b11000011 %
1*
b111100 "
b111100 &
0)
1#
#123
0#
#124
1+
b11 '
b11000010 %
0*
b111101 "
b111101 &
1)
1#
#125
0#
#126
0+
b1 '
1-
0,
b11000001 %
1*
b111110 "
b111110 &
0)
1#
#127
0#
#128
1:
17
14
11
1.
1+
b1111111 '
b11000000 %
0*
b111111 "
b111111 &
1)
1#
#129
0#
#130
0:
07
04
01
0.
0+
b1 '
1<
0;
09
18
06
15
03
12
00
1/
0-
1,
b10111111 %
1*
b1000000 "
b1000000 &
0)
1#
#131
0#
#132
1+
b11 '
b10111110 %
0*
b1000001 "
b1000001 &
1)
1#
#133
0#
#134
0+
b1 '
1-
0,
b10111101 %
1*
b1000010 "
b1000010 &
0)
1#
#135
0#
#136
1.
1+
b111 '
b10111100 %
0*
b1000011 "
b1000011 &
1)
1#
#137
0#
#138
0.
0+
b1 '
10
0/
0-
1,
b10111011 %
1*
b1000100 "
b1000100 &
0)
1#
#139
0#
#140
1+
b11 '
b10111010 %
0*
b1000101 "
b1000101 &
1)
1#
#141
0#
#142
0+
b1 '
1-
0,
b10111001 %
1*
b1000110 "
b1000110 &
0)
1#
#143
0#
#144
11
1.
1+
b1111 '
b10111000 %
0*
b1000111 "
b1000111 &
1)
1#
#145
0#
#146
01
0.
0+
b1 '
13
02
00
1/
0-
1,
b10110111 %
1*
b1001000 "
b1001000 &
0)
1#
#147
0#
#148
1+
b11 '
b10110110 %
0*
b1001001 "
b1001001 &
1)
1#
#149
0#
#150
0+
b1 '
1-
0,
b10110101 %
1*
b1001010 "
b1001010 &
0)
1#
#151
0#
#152
1.
1+
b111 '
b10110100 %
0*
b1001011 "
b1001011 &
1)
1#
#153
0#
#154
0.
0+
b1 '
10
0/
0-
1,
b10110011 %
1*
b1001100 "
b1001100 &
0)
1#
#155
0#
#156
1+
b11 '
b10110010 %
0*
b1001101 "
b1001101 &
1)
1#
#157
0#
#158
0+
b1 '
1-
0,
b10110001 %
1*
b1001110 "
b1001110 &
0)
1#
#159
0#
#160
14
11
1.
1+
b11111 '
b10110000 %
0*
b1001111 "
b1001111 &
1)
1#
#161
0#
#162
04
01
0.
0+
b1 '
16
05
03
12
00
1/
0-
1,
b10101111 %
1*
b1010000 "
b1010000 &
0)
1#
#163
0#
#164
1+
b11 '
b10101110 %
0*
b1010001 "
b1010001 &
1)
1#
#165
0#
#166
0+
b1 '
1-
0,
b10101101 %
1*
b1010010 "
b1010010 &
0)
1#
#167
0#
#168
1.
1+
b111 '
b10101100 %
0*
b1010011 "
b1010011 &
1)
1#
#169
0#
#170
0.
0+
b1 '
10
0/
0-
1,
b10101011 %
1*
b1010100 "
b1010100 &
0)
1#
#171
0#
#172
1+
b11 '
b10101010 %
0*
b1010101 "
b1010101 &
1)
1#
#173
0#
#174
0+
b1 '
1-
0,
b10101001 %
1*
b1010110 "
b1010110 &
0)
1#
#175
0#
#176
11
1.
1+
b1111 '
b10101000 %
0*
b1010111 "
b1010111 &
1)
1#
#177
0#
#178
01
0.
0+
b1 '
13
02
00
1/
0-
1,
b10100111 %
1*
b1011000 "
b1011000 &
0)
1#
#179
0#
#180
1+
b11 '
b10100110 %
0*
b1011001 "
b1011001 &
1)
1#
#181
0#
#182
0+
b1 '
1-
0,
b10100101 %
1*
b1011010 "
b1011010 &
0)
1#
#183
0#
#184
1.
1+
b111 '
b10100100 %
0*
b1011011 "
b1011011 &
1)
1#
#185
0#
#186
0.
0+
b1 '
10
0/
0-
1,
b10100011 %
1*
b1011100 "
b1011100 &
0)
1#
#187
0#
#188
1+
b11 '
b10100010 %
0*
b1011101 "
b1011101 &
1)
1#
#189
0#
#190
0+
b1 '
1-
0,
b10100001 %
1*
b1011110 "
b1011110 &
0)
1#
#191
0#
#192
17
14
11
1.
1+
b111111 '
b10100000 %
0*
b1011111 "
b1011111 &
1)
1#
#193
0#
#194
07
04
01
0.
0+
b1 '
19
08
06
15
03
12
00
1/
0-
1,
b10011111 %
1*
b1100000 "
b1100000 &
0)
1#
#195
0#
#196
1+
b11 '
b10011110 %
0*
b1100001 "
b1100001 &
1)
1#
#197
0#
#198
0+
b1 '
1-
0,
b10011101 %
1*
b1100010 "
b1100010 &
0)
1#
#199
0#
#200
1.
1+
b111 '
b10011100 %
0*
b1100011 "
b1100011 &
1)
1#
#201
0#
#202
0.
0+
b1 '
10
0/
0-
1,
b10011011 %
1*
b1100100 "
b1100100 &
0)
1#
#203
0#
#204
1+
b11 '
b10011010 %
0*
b1100101 "
b1100101 &
1)
1#
#205
0#
#206
0+
b1 '
1-
0,
b10011001 %
1*
b1100110 "
b1100110 &
0)
1#
#207
0#
#208
11
1.
1+
b1111 '
b10011000 %
0*
b1100111 "
b1100111 &
1)
1#
#209
0#
#210
01
0.
0+
b1 '
13
02
00
1/
0-
1,
b10010111 %
1*
b1101000 "
b1101000 &
0)
1#
#211
0#
#212
1+
b11 '
b10010110 %
0*
b1101001 "
b1101001 &
1)
1#
#213
0#
#214
0+
b1 '
1-
0,
b10010101 %
1*
b1101010 "
b1101010 &
0)
1#
#215
0#
#216
1.
1+
b111 '
b10010100 %
0*
b1101011 "
b1101011 &
1)
1#
#217
0#
#218
0.
0+
b1 '
10
0/
0-
1,
b10010011 %
1*
b1101100 "
b1101100 &
0)
1#
#219
0#
#220
1+
b11 '
b10010010 %
0*
b1101101 "
b1101101 &
1)
1#
#221
0#
#222
0+
b1 '
1-
0,
b10010001 %
1*
b1101110 "
b1101110 &
0)
1#
#223
0#
#224
14
11
1.
1+
b11111 '
b10010000 %
0*
b1101111 "
b1101111 &
1)
1#
#225
0#
#226
04
01
0.
0+
b1 '
16
05
03
12
00
1/
0-
1,
b10001111 %
1*
b1110000 "
b1110000 &
0)
1#
#227
0#
#228
1+
b11 '
b10001110 %
0*
b1110001 "
b1110001 &
1)
1#
#229
0#
#230
0+
b1 '
1-
0,
b10001101 %
1*
b1110010 "
b1110010 &
0)
1#
#231
0#
#232
1.
1+
b111 '
b10001100 %
0*
b1110011 "
b1110011 &
1)
1#
#233
0#
#234
0.
0+
b1 '
10
0/
0-
1,
b10001011 %
1*
b1110100 "
b1110100 &
0)
1#
#235
0#
#236
1+
b11 '
b10001010 %
0*
b1110101 "
b1110101 &
1)
1#
#237
0#
#238
0+
b1 '
1-
0,
b10001001 %
1*
b1110110 "
b1110110 &
0)
1#
#239
0#
#240
11
1.
1+
b1111 '
b10001000 %
0*
b1110111 "
b1110111 &
1)
1#
#241
0#
#242
01
0.
0+
b1 '
13
02
00
1/
0-
1,
b10000111 %
1*
b1111000 "
b1111000 &
0)
1#
#243
0#
#244
1+
b11 '
b10000110 %
0*
b1111001 "
b1111001 &
1)
1#
#245
0#
#246
0+
b1 '
1-
0,
b10000101 %
1*
b1111010 "
b1111010 &
0)
1#
#247
0#
#248
1.
1+
b111 '
b10000100 %
0*
b1111011 "
b1111011 &
1)
1#
#249
0#
#250
0.
0+
b1 '
10
0/
0-
1,
b10000011 %
1*
b1111100 "
b1111100 &
0)
1#
#251
0#
#252
1+
b11 '
b10000010 %
0*
b1111101 "
b1111101 &
1)
1#
#253
0#
#254
0+
b1 '
1-
0,
b10000001 %
1*
b1111110 "
b1111110 &
0)
1#
#255
0#
#256
1=
1:
17
14
11
1.
1+
b11111111 '
b10000000 %
0*
b1111111 "
b1111111 &
1)
1#
#257
0#
#258
0=
0:
07
04
01
0.
0+
b1 '
1?
0>
0<
1;
09
18
06
15
03
12
00
1/
0-
1,
b1111111 %
1*
b10000000 "
b10000000 &
0)
1#
#259
0#
#260
1+
b11 '
b1111110 %
0*
b10000001 "
b10000001 &
1)
1#
#261
0#
#262
0+
b1 '
1-
0,
b1111101 %
1*
b10000010 "
b10000010 &
0)
1#
#263
0#
#264
1.
1+
b111 '
b1111100 %
0*
b10000011 "
b10000011 &
1)
1#
#265
0#
#266
0.
0+
b1 '
10
0/
0-
1,
b1111011 %
1*
b10000100 "
b10000100 &
0)
1#
#267
0#
#268
1+
b11 '
b1111010 %
0*
b10000101 "
b10000101 &
1)
1#
#269
0#
#270
0+
b1 '
1-
0,
b1111001 %
1*
b10000110 "
b10000110 &
0)
1#
#271
0#
#272
11
1.
1+
b1111 '
b1111000 %
0*
b10000111 "
b10000111 &
1)
1#
#273
0#
#274
01
0.
0+
b1 '
13
02
00
1/
0-
1,
b1110111 %
1*
b10001000 "
b10001000 &
0)
1#
#275
0#
#276
1+
b11 '
b1110110 %
0*
b10001001 "
b10001001 &
1)
1#
#277
0#
#278
0+
b1 '
1-
0,
b1110101 %
1*
b10001010 "
b10001010 &
0)
1#
#279
0#
#280
1.
1+
b111 '
b1110100 %
0*
b10001011 "
b10001011 &
1)
1#
#281
0#
#282
0.
0+
b1 '
10
0/
0-
1,
b1110011 %
1*
b10001100 "
b10001100 &
0)
1#
#283
0#
#284
1+
b11 '
b1110010 %
0*
b10001101 "
b10001101 &
1)
1#
#285
0#
#286
0+
b1 '
1-
0,
b1110001 %
1*
b10001110 "
b10001110 &
0)
1#
#287
0#
#288
14
11
1.
1+
b11111 '
b1110000 %
0*
b10001111 "
b10001111 &
1)
1#
#289
0#
#290
04
01
0.
0+
b1 '
16
05
03
12
00
1/
0-
1,
b1101111 %
1*
b10010000 "
b10010000 &
0)
1#
#291
0#
#292
1+
b11 '
b1101110 %
0*
b10010001 "
b10010001 &
1)
1#
#293
0#
#294
0+
b1 '
1-
0,
b1101101 %
1*
b10010010 "
b10010010 &
0)
1#
#295
0#
#296
1.
1+
b111 '
b1101100 %
0*
b10010011 "
b10010011 &
1)
1#
#297
0#
#298
0.
0+
b1 '
10
0/
0-
1,
b1101011 %
1*
b10010100 "
b10010100 &
0)
1#
#299
0#
#300
1+
b11 '
b1101010 %
0*
b10010101 "
b10010101 &
1)
1#
#301
0#
#302
0+
b1 '
1-
0,
b1101001 %
1*
b10010110 "
b10010110 &
0)
1#
#303
0#
#304
11
1.
1+
b1111 '
b1101000 %
0*
b10010111 "
b10010111 &
1)
1#
#305
0#
#306
01
0.
0+
b1 '
13
02
00
1/
0-
1,
b1100111 %
1*
b10011000 "
b10011000 &
0)
1#
#307
0#
#308
1+
b11 '
b1100110 %
0*
b10011001 "
b10011001 &
1)
1#
#309
0#
#310
0+
b1 '
1-
0,
b1100101 %
1*
b10011010 "
b10011010 &
0)
1#
#311
0#
#312
1.
1+
b111 '
b1100100 %
0*
b10011011 "
b10011011 &
1)
1#
#313
0#
#314
0.
0+
b1 '
10
0/
0-
1,
b1100011 %
1*
b10011100 "
b10011100 &
0)
1#
#315
0#
#316
1+
b11 '
b1100010 %
0*
b10011101 "
b10011101 &
1)
1#
#317
0#
#318
0+
b1 '
1-
0,
b1100001 %
1*
b10011110 "
b10011110 &
0)
1#
#319
0#
#320
17
14
11
1.
1+
b111111 '
b1100000 %
0*
b10011111 "
b10011111 &
1)
1#
#321
0#
#322
07
04
01
0.
0+
b1 '
19
08
06
15
03
12
00
1/
0-
1,
b1011111 %
1*
b10100000 "
b10100000 &
0)
1#
#323
0#
#324
1+
b11 '
b1011110 %
0*
b10100001 "
b10100001 &
1)
1#
#325
0#
#326
0+
b1 '
1-
0,
b1011101 %
1*
b10100010 "
b10100010 &
0)
1#
#327
0#
#328
1.
1+
b111 '
b1011100 %
0*
b10100011 "
b10100011 &
1)
1#
#329
0#
#330
0.
0+
b1 '
10
0/
0-
1,
b1011011 %
1*
b10100100 "
b10100100 &
0)
1#
#331
0#
#332
1+
b11 '
b1011010 %
0*
b10100101 "
b10100101 &
1)
1#
#333
0#
#334
0+
b1 '
1-
0,
b1011001 %
1*
b10100110 "
b10100110 &
0)
1#
#335
0#
#336
11
1.
1+
b1111 '
b1011000 %
0*
b10100111 "
b10100111 &
1)
1#
#337
0#
#338
01
0.
0+
b1 '
13
02
00
1/
0-
1,
b1010111 %
1*
b10101000 "
b10101000 &
0)
1#
#339
0#
#340
1+
b11 '
b1010110 %
0*
b10101001 "
b10101001 &
1)
1#
#341
0#
#342
0+
b1 '
1-
0,
b1010101 %
1*
b10101010 "
b10101010 &
0)
1#
#343
0#
#344
1.
1+
b111 '
b1010100 %
0*
b10101011 "
b10101011 &
1)
1#
#345
0#
#346
0.
0+
b1 '
10
0/
0-
1,
b1010011 %
1*
b10101100 "
b10101100 &
0)
1#
#347
0#
#348
1+
b11 '
b1010010 %
0*
b10101101 "
b10101101 &
1)
1#
#349
0#
#350
0+
b1 '
1-
0,
b1010001 %
1*
b10101110 "
b10101110 &
0)
1#
#351
0#
#352
14
11
1.
1+
b11111 '
b1010000 %
0*
b10101111 "
b10101111 &
1)
1#
#353
0#
#354
04
01
0.
0+
b1 '
16
05
03
12
00
1/
0-
1,
b1001111 %
1*
b10110000 "
b10110000 &
0)
1#
#355
0#
#356
1+
b11 '
b1001110 %
0*
b10110001 "
b10110001 &
1)
1#
#357
0#
#358
0+
b1 '
1-
0,
b1001101 %
1*
b10110010 "
b10110010 &
0)
1#
#359
0#
#360
1.
1+
b111 '
b1001100 %
0*
b10110011 "
b10110011 &
1)
1#
#361
0#
#362
0.
0+
b1 '
10
0/
0-
1,
b1001011 %
1*
b10110100 "
b10110100 &
0)
1#
#363
0#
#364
1+
b11 '
b1001010 %
0*
b10110101 "
b10110101 &
1)
1#
#365
0#
#366
0+
b1 '
1-
0,
b1001001 %
1*
b10110110 "
b10110110 &
0)
1#
#367
0#
#368
11
1.
1+
b1111 '
b1001000 %
0*
b10110111 "
b10110111 &
1)
1#
#369
0#
#370
01
0.
0+
b1 '
13
02
00
1/
0-
1,
b1000111 %
1*
b10111000 "
b10111000 &
0)
1#
#371
0#
#372
1+
b11 '
b1000110 %
0*
b10111001 "
b10111001 &
1)
1#
#373
0#
#374
0+
b1 '
1-
0,
b1000101 %
1*
b10111010 "
b10111010 &
0)
1#
#375
0#
#376
1.
1+
b111 '
b1000100 %
0*
b10111011 "
b10111011 &
1)
1#
#377
0#
#378
0.
0+
b1 '
10
0/
0-
1,
b1000011 %
1*
b10111100 "
b10111100 &
0)
1#
#379
0#
#380
1+
b11 '
b1000010 %
0*
b10111101 "
b10111101 &
1)
1#
#381
0#
#382
0+
b1 '
1-
0,
b1000001 %
1*
b10111110 "
b10111110 &
0)
1#
#383
0#
#384
1:
17
14
11
1.
1+
b1111111 '
b1000000 %
0*
b10111111 "
b10111111 &
1)
1#
#385
0#
#386
0:
07
04
01
0.
0+
b1 '
1<
0;
09
18
06
15
03
12
00
1/
0-
1,
b111111 %
1*
b11000000 "
b11000000 &
0)
1#
#387
0#
#388
1+
b11 '
b111110 %
0*
b11000001 "
b11000001 &
1)
1#
#389
0#
#390
0+
b1 '
1-
0,
b111101 %
1*
b11000010 "
b11000010 &
0)
1#
#391
0#
#392
1.
1+
b111 '
b111100 %
0*
b11000011 "
b11000011 &
1)
1#
#393
0#
#394
0.
0+
b1 '
10
0/
0-
1,
b111011 %
1*
b11000100 "
b11000100 &
0)
1#
#395
0#
#396
1+
b11 '
b111010 %
0*
b11000101 "
b11000101 &
1)
1#
#397
0#
#398
0+
b1 '
1-
0,
b111001 %
1*
b11000110 "
b11000110 &
0)
1#
#399
0#
#400
11
1.
1+
b1111 '
b111000 %
0*
b11000111 "
b11000111 &
1)
1#
#401
0#
#402
01
0.
0+
b1 '
13
02
00
1/
0-
1,
b110111 %
1*
b11001000 "
b11001000 &
0)
1#
#403
0#
#404
1+
b11 '
b110110 %
0*
b11001001 "
b11001001 &
1)
1#
#405
0#
#406
0+
b1 '
1-
0,
b110101 %
1*
b11001010 "
b11001010 &
0)
1#
#407
0#
#408
1.
1+
b111 '
b110100 %
0*
b11001011 "
b11001011 &
1)
1#
#409
0#
#410
0.
0+
b1 '
10
0/
0-
1,
b110011 %
1*
b11001100 "
b11001100 &
0)
1#
#411
0#
#412
1+
b11 '
b110010 %
0*
b11001101 "
b11001101 &
1)
1#
#413
0#
#414
0+
b1 '
1-
0,
b110001 %
1*
b11001110 "
b11001110 &
0)
1#
#415
0#
#416
14
11
1.
1+
b11111 '
b110000 %
0*
b11001111 "
b11001111 &
1)
1#
#417
0#
#418
04
01
0.
0+
b1 '
16
05
03
12
00
1/
0-
1,
b101111 %
1*
b11010000 "
b11010000 &
0)
1#
#419
0#
#420
1+
b11 '
b101110 %
0*
b11010001 "
b11010001 &
1)
1#
#421
0#
#422
0+
b1 '
1-
0,
b101101 %
1*
b11010010 "
b11010010 &
0)
1#
#423
0#
#424
1.
1+
b111 '
b101100 %
0*
b11010011 "
b11010011 &
1)
1#
#425
0#
#426
0.
0+
b1 '
10
0/
0-
1,
b101011 %
1*
b11010100 "
b11010100 &
0)
1#
#427
0#
#428
1+
b11 '
b101010 %
0*
b11010101 "
b11010101 &
1)
1#
#429
0#
#430
0+
b1 '
1-
0,
b101001 %
1*
b11010110 "
b11010110 &
0)
1#
#431
0#
#432
11
1.
1+
b1111 '
b101000 %
0*
b11010111 "
b11010111 &
1)
1#
#433
0#
#434
01
0.
0+
b1 '
13
02
00
1/
0-
1,
b100111 %
1*
b11011000 "
b11011000 &
0)
1#
#435
0#
#436
1+
b11 '
b100110 %
0*
b11011001 "
b11011001 &
1)
1#
#437
0#
#438
0+
b1 '
1-
0,
b100101 %
1*
b11011010 "
b11011010 &
0)
1#
#439
0#
#440
1.
1+
b111 '
b100100 %
0*
b11011011 "
b11011011 &
1)
1#
#441
0#
#442
0.
0+
b1 '
10
0/
0-
1,
b100011 %
1*
b11011100 "
b11011100 &
0)
1#
#443
0#
#444
1+
b11 '
b100010 %
0*
b11011101 "
b11011101 &
1)
1#
#445
0#
#446
0+
b1 '
1-
0,
b100001 %
1*
b11011110 "
b11011110 &
0)
1#
#447
0#
#448
17
14
11
1.
1+
b111111 '
b100000 %
0*
b11011111 "
b11011111 &
1)
1#
#449
0#
#450
07
04
01
0.
0+
b1 '
19
08
06
15
03
12
00
1/
0-
1,
b11111 %
1*
b11100000 "
b11100000 &
0)
1#
#451
0#
#452
1+
b11 '
b11110 %
0*
b11100001 "
b11100001 &
1)
1#
#453
0#
#454
0+
b1 '
1-
0,
b11101 %
1*
b11100010 "
b11100010 &
0)
1#
#455
0#
#456
1.
1+
b111 '
b11100 %
0*
b11100011 "
b11100011 &
1)
1#
#457
0#
#458
0.
0+
b1 '
10
0/
0-
1,
b11011 %
1*
b11100100 "
b11100100 &
0)
1#
#459
0#
#460
1+
b11 '
b11010 %
0*
b11100101 "
b11100101 &
1)
1#
#461
0#
